LICENSE
README.rst
setup.py
igcommit/__init__.py
igcommit/base_check.py
igcommit/commit_checks.py
igcommit/commit_list_checks.py
igcommit/config.py
igcommit/file_checks.py
igcommit/git.py
igcommit/prereceive.py
igcommit/utils.py
igcommit.egg-info/PKG-INFO
igcommit.egg-info/SOURCES.txt
igcommit.egg-info/dependency_links.txt
igcommit.egg-info/entry_points.txt
igcommit.egg-info/top_level.txt