Metadata-Version: 2.1
Name: igcommit
Version: 3.2
Summary: Git pre-receive hook to check commits and code style
Home-page: https://github.com/innogames/igcommit
Author: InnoGames System Administration
Author-email: it@innogames.com
License: MIT
Keywords: syntax-checker git git-hook python csslint golint htmlhint puppet puppet-lint flake8 pycodestyle pyflakes rubocop shellcheck eslint jshint jscs standard coffeelint phpcs
Platform: POSIX
License-File: LICENSE
